setup.py
kamal_indian_states_25/__init__.py
kamal_indian_states_25/asgi.py
kamal_indian_states_25/settings.py
kamal_indian_states_25/urls.py
kamal_indian_states_25/wsgi.py
kamal_indian_states_25.egg-info/PKG-INFO
kamal_indian_states_25.egg-info/SOURCES.txt
kamal_indian_states_25.egg-info/dependency_links.txt
kamal_indian_states_25.egg-info/requires.txt
kamal_indian_states_25.egg-info/top_level.txt
kst1/__init__.py
kst1/admin.py
kst1/apps.py
kst1/fields.py
kst1/forms.py
kst1/models.py
kst1/states.py
kst1/tests.py
kst1/views.py
kst1/migrations/__init__.py